dcsv.py
dscv-1.0.2.dist-info/LICENSE
dscv-1.0.2.dist-info/METADATA
dscv-1.0.2.dist-info/WHEEL
dscv-1.0.2.dist-info/top_level.txt
dscv-1.0.2.dist-info/RECORD
