Metadata-Version: 2.1
Name: dscv
Version: 1.0.2
Summary: Module for parsing and writing DCMI structured value strings
Author-email: Erkka Rinne <erkka.rinne@fmi.fi>
Classifier: Programming Language :: Python :: 3
Classifier: License :: OSI Approved :: MIT License
Classifier: Operating System :: OS Independent
Requires-Python: >=3.9
License-File: LICENSE
Provides-Extra: develop
Requires-Dist: pylint ; extra == 'develop'
Requires-Dist: black ; extra == 'develop'
Provides-Extra: test
Requires-Dist: pytest ; extra == 'test'
